Metadata-Version: 1.1
Name: allthingstalk
Version: 0.2.5
Summary: AllThingsTalk Python SDK
Home-page: https://github.com/allthingstalk/python-sdk
Author: Danilo Vidovic
Author-email: dv@allthingstalk.com
License: Apache 2.0
Download-URL: https://github.com/allthingstalk/python-sdk/archive/0.2.5.tar.gz
Keywords: allthingstalk,iot,sdk
Platform: UNKNOWN
Classifier: Development Status :: 4 - Beta
Classifier: Environment :: Console
Classifier: Intended Audience :: Developers
Classifier: License :: OSI Approved :: Apache Software License
Classifier: Operating System :: MacOS :: MacOS X
Classifier: Operating System :: Microsoft :: Windows
Classifier: Operating System :: POSIX
Classifier: Topic :: Internet
Classifier: Topic :: Software Development :: Libraries
Classifier: Programming Language :: Python
Classifier: Programming Language :: Python :: 3.4
Classifier: Programming Language :: Python :: 3.5
Classifier: Programming Language :: Python :: 3.6
Classifier: Programming Language :: Python :: 3 :: Only
